sun2000_modbus/__init__.py
sun2000_modbus/datatypes.py
sun2000_modbus/inverter.py
sun2000_modbus/mappings.py
sun2000_modbus/registers.py
sun2000_modbus-3.0.0.dist-info/licenses/LICENSE
sun2000_modbus-3.0.0.dist-info/WHEEL
sun2000_modbus-3.0.0.dist-info/METADATA
sun2000_modbus-3.0.0.dist-info/RECORD
