Metadata-Version: 2.4
Name: sun2000_modbus
Version: 3.0.0
Summary: Library for reading Huawei Sun2000 inverter metrics via Modbus TCP
Keywords: sun2000,modbus,photovoltaic
Author-email: Oliver Gregorius <oliver@gregorius.dev>
Requires-Python: >=3.9
Classifier: Programming Language :: Python :: 3
Classifier: License :: OSI Approved :: MIT License
Classifier: Intended Audience :: Developers
Classifier: Topic :: Software Development :: Libraries :: Python Modules
License-File: LICENSE
Requires-Dist: pymodbus>=3.11.0
Project-URL: Source, https://github.com/olivergregorius/sun2000_modbus
